{"type":"header","name":"t:labels.header_group","sections":{"toolbar":{"type":"toolbar","blocks":{"toolbar-0":{"type":"announcement","settings":{"richtext":"<p>Hassle-free returns. 30-day postage paid returns<\/p>","richtext_mobile":""}},"toolbar-1":{"type":"announcement","settings":{"richtext":"<p>Hassle-free returns. 30-day postage paid returns<\/p>","richtext_mobile":""}}},"block_order":["toolbar-0","toolbar-1"],"disabled":true,"settings":{"announcement_center":false,"toolbar_social":true,"show_locale_selector":false,"show_currency_selector":false,"show_currency_flags":false}},"header":{"type":"header","blocks":{"logo_fhxnpr":{"type":"logo","settings":{"logo":"shopify:\/\/shop_images\/Plast_Bat-01.png","desktop_logo_width":130,"mobile_logo_width":100}}},"block_order":["logo_fhxnpr"],"settings":{"main_menu_link_list":"main-menu-1","hover_menu":true,"main_menu_alignment":"center","mega_products":true,"header_sticky":false,"header_footer_menu":true,"sticky_index":false,"sticky_collection":true}}},"order":["toolbar","header"]}